pbsrollout/__init__.py
pbsrollout/internal/__init__.py
pbsrollout/internal/aws_utils.py
pbsrollout/internal/check_cluster_ready.py
pbsrollout/internal/k8s_utils.py
pbsrollout/internal/process_cluster.py
pbsrollout/internal/test_aws_utils.py
pbsrollout/internal/test_k8s_utils.py
pbsrollout/internal/test_process_cluster.py
pbsrollout/internal/test_utils.py
pbsrollout/internal/test_utils_gh.py
pbsrollout/internal/utils.py
pbsrollout/internal/utils_gh.py
pbsrollout/main.py
pbsrollout/pbs_release/__init__.py
pbsrollout/pbs_release/main_view.py
pbsrollout/stg_release/__init__.py
pbsrollout/stg_release/main_view.py
pbsrollout/test_main.py
pbsrollout-0.4.dist-info/LICENSE
pbsrollout-0.4.dist-info/METADATA
pbsrollout-0.4.dist-info/WHEEL
pbsrollout-0.4.dist-info/entry_points.txt
pbsrollout-0.4.dist-info/RECORD
